pygamebox/__init__.py
pygamebox/guess_the_number.py
pygamebox/hangman.py
pygamebox/rock_paper_scissors.py
pygamebox/utils.py
pygamebox/word_scramble.py
pygamebox/wordle.py
pygamebox/data/valid_wordle_words.txt
pygamebox/data/wordle_possibilities.txt
pygamebox/data/words.txt
pygamebox-0.0.2.dist-info/LICENSE
pygamebox-0.0.2.dist-info/METADATA
pygamebox-0.0.2.dist-info/WHEEL
pygamebox-0.0.2.dist-info/top_level.txt
pygamebox-0.0.2.dist-info/RECORD
