Metadata-Version: 2.1
Name: pygamebox
Version: 0.0.2
Summary: A Python package for simple text-based games.
Author-email: Aavishkar Gautam <ag8298@nyu.edu>, Avaneesh Devkota <ad5768@nyu.edu>, Soyuj Jung Basnet <soyuj@nyu.edu>
License: GNU GENERAL PUBLIC LICENSE
Project-URL: Homepage, https://github.com/software-students-fall2023/3-python-package-exercise-prime-order
Project-URL: Bug Tracker, https://github.com/software-students-fall2023/3-python-package-exercise-prime-order/issues
Keywords: python,package,games,pygamebox,hangman,wordle,word-scramble,guess-the-number,rock-paper-scissors
Classifier: Programming Language :: Python :: 3
Classifier: Intended Audience :: Education
Classifier: License :: OSI Approved :: GNU General Public License v3 (GPLv3)
Classifier: Operating System :: OS Independent
Requires-Python: >=3.7
License-File: LICENSE
Requires-Dist: colorama
